{
  "main": {
    "id": "808b520aad639fd2",
    "type": "split",
    "children": [
      {
        "id": "17ac83abd6afb61f",
        "type": "tabs",
        "children": [
          {
            "id": "f4dc31178ee957f8",
            "type": "leaf",
            "state": {
              "type": "markdown",
              "state": {
                "file": "about.md",
                "mode": "source",
                "source": false
              }
            }
          }
        ]
      }
    ],
    "direction": "vertical"
  },
  "left": {
    "id": "3b508cc5f28b309b",
    "type": "split",
    "children": [
      {
        "id": "b2a1d031de3244e8",
        "type": "tabs",
        "children": [
          {
            "id": "57e015ff34c6c0c1",
            "type": "leaf",
            "state": {
              "type": "file-explorer",
              "state": {
                "sortOrder": "alphabetical"
              }
            }
          },
          {
            "id": "8ef5dd6383f158a9",
            "type": "leaf",
            "state": {
              "type": "search",
              "state": {
                "query": "",
                "matchingCase": false,
                "explainSearch": false,
                "collapseAll": false,
                "extraContext": false,
                "sortOrder": "alphabetical"
              }
            }
          },
          {
            "id": "ce4b581943efdf6c",
            "type": "leaf",
            "state": {
              "type": "bookmarks",
              "state": {}
            }
          }
        ]
      }
    ],
    "direction": "horizontal",
    "width": 300
  },
  "right": {
    "id": "0415bf0ca041c551",
    "type": "split",
    "children": [
      {
        "id": "6856b92185fbf066",
        "type": "tabs",
        "children": [
          {
            "id": "2824f14bb230a11d",
            "type": "leaf",
            "state": {
              "type": "backlink",
              "state": {
                "file": "about.md",
                "collapseAll": false,
                "extraContext": false,
                "sortOrder": "alphabetical",
                "showSearch": false,
                "searchQuery": "",
                "backlinkCollapsed": false,
                "unlinkedCollapsed": true
              }
            }
          },
          {
            "id": "cd81de03281a1b05",
            "type": "leaf",
            "state": {
              "type": "outgoing-link",
              "state": {
                "file": "about.md",
                "linksCollapsed": false,
                "unlinkedCollapsed": true
              }
            }
          },
          {
            "id": "ad89ef5804b49b3a",
            "type": "leaf",
            "state": {
              "type": "tag",
              "state": {
                "sortOrder": "frequency",
                "useHierarchy": true
              }
            }
          },
          {
            "id": "1a02cdf6ee880a35",
            "type": "leaf",
            "state": {
              "type": "outline",
              "state": {
                "file": "about.md"
              }
            }
          }
        ]
      }
    ],
    "direction": "horizontal",
    "width": 300,
    "collapsed": true
  },
  "left-ribbon": {
    "hiddenItems": {
      "switcher:Меню быстрого перехода": false,
      "graph:Граф": false,
      "canvas:Создать новый холст": false,
      "daily-notes:Сегодняшняя заметка": false,
      "templates:Вставить шаблон": false,
      "command-palette:Открыть палитру команд": false
    }
  },
  "active": "f4dc31178ee957f8",
  "lastOpenFiles": [
    "README.md"
  ]
}